rtl/alu.v
module alu (
    input  [7:0] A,
    input  [7:0] B,
    input  [2:0] ALU_SEL,
    output reg [7:0] RESULT,
    output reg       ZERO
);

    always @(*) begin

        case (ALU_SEL)

            3'b000: RESULT = A + B;       // ADD
            3'b001: RESULT = A - B;       // SUB
            3'b010: RESULT = A & B;       // AND
            3'b011: RESULT = A | B;       // OR
            3'b100: RESULT = A ^ B;       // XOR
            3'b101: RESULT = ~A;          // NOT
            3'b110: RESULT = A + 8'd1;    // INCREMENT
            3'b111: RESULT = A - 8'd1;    // DECREMENT

            default: RESULT = 8'b0;

        endcase

        if (RESULT == 8'b0)
            ZERO = 1'b1;
        else
            ZERO = 1'b0;

    end

endmodule

tb/alu_tb.v
`timescale 1ns/1ps

module alu_tb;

    reg  [7:0] A;
    reg  [7:0] B;
    reg  [2:0] ALU_SEL;

    wire [7:0] RESULT;
    wire       ZERO;

    alu uut (
        .A(A),
        .B(B),
        .ALU_SEL(ALU_SEL),
        .RESULT(RESULT),
        .ZERO(ZERO)
    );

    task test_operation;
        input [2:0] sel;
        input [7:0] a;
        input [7:0] b;

        begin
            A = a;
            B = b;
            ALU_SEL = sel;

            #10;

            $display(
                "A=%h B=%h SEL=%b RESULT=%h ZERO=%b",
                A, B, ALU_SEL, RESULT, ZERO
            );
        end
    endtask

    initial begin

        $dumpfile("simulation/alu.vcd");
        $dumpvars(0, alu_tb);

        $display("======================================");
        $display("       8-BIT RISC PROCESSOR ALU       ");
        $display("======================================");

        test_operation(3'b000, 8'd10, 8'd5);   // ADD
        test_operation(3'b001, 8'd10, 8'd5);   // SUB
        test_operation(3'b010, 8'hF0, 8'h0F);  // AND
        test_operation(3'b011, 8'hF0, 8'h0F);  // OR
        test_operation(3'b100, 8'hAA, 8'h55);  // XOR
        test_operation(3'b101, 8'h0F, 8'd0);   // NOT
        test_operation(3'b110, 8'd10, 8'd0);   // INCREMENT
        test_operation(3'b111, 8'd10, 8'd0);   // DECREMENT

        $display("======================================");
        $display("             ALU TEST DONE            ");
        $display("======================================");

        #10;
        $finish;

    end

endmodule

simulation/alu.vcd
$date
	Wed Aug 26 21:40:54 2026
$end
$version
	Icarus Verilog
$end
$timescale
	1ps
$end
$scope module alu_tb $end
$var wire 1 ! ZERO $end
$var wire 8 " RESULT [7:0] $end
$var reg 8 # A [7:0] $end
$var reg 3 $ ALU_SEL [2:0] $end
$var reg 8 % B [7:0] $end
$scope module uut $end
$var wire 8 & A [7:0] $end
$var wire 3 ' ALU_SEL [2:0] $end
$var wire 8 ( B [7:0] $end
$var reg 8 ) RESULT [7:0] $end
$var reg 1 ! ZERO $end
$upscope $end
$scope task test_operation $end
$var reg 8 * a [7:0] $end
$var reg 8 + b [7:0] $end
$var reg 3 , sel [2:0] $end
$upscope $end
$upscope $end
$enddefinitions $end
$comment Show the parameter values. $end
$dumpall
$end
#0
$dumpvars
b0 ,
b101 +
b1010 *
b1111 )
b101 (
b0 '
b1010 &
b101 %
b0 $
b1010 #
b1111 "
0!
$end
#10000
b101 "
b101 )
b1 $
b1 '
b1 ,
#20000
1!
b0 "
b0 )
b10 $
b10 '
b1111 %
b1111 (
b11110000 #
b11110000 &
b1111 +
b11110000 *
b10 ,
#30000
0!
b11111111 "
b11111111 )
b11 $
b11 '
b11 ,
#40000
b100 $
b100 '
b1010101 %
b1010101 (
b10101010 #
b10101010 &
b1010101 +
b10101010 *
b100 ,
#50000
b11110000 "
b11110000 )
b101 $
b101 '
b0 %
b0 (
b1111 #
b1111 &
b0 +
b1111 *
b101 ,
#60000
b1011 "
b1011 )
b110 $
b110 '
b1010 #
b1010 &
b1010 *
b110 ,
#70000
b1001 "
b1001 )
b111 $
b111 '
b111 ,
