rtl/data_memory.v
module data_memory (
    input        clk,
    input        mem_read,
    input        mem_write,

    input  [7:0] address,
    input  [7:0] write_data,

    output [7:0] read_data
);

    reg [7:0] memory [0:255];

    // Read operation
    assign read_data = mem_read ? memory[address] : 8'b0;

    // Write operation
    always @(posedge clk) begin
        if (mem_write)
            memory[address] <= write_data;
    end

endmodule

rtl/alu.v
module alu (
    input  [7:0] A,
    input  [7:0] B,
    input  [2:0] ALU_SEL,
    output reg [7:0] RESULT,
    output reg       ZERO
);

    always @(*) begin

        case (ALU_SEL)

            3'b000: RESULT = A + B;       // ADD
            3'b001: RESULT = A - B;       // SUB
            3'b010: RESULT = A & B;       // AND
            3'b011: RESULT = A | B;       // OR
            3'b100: RESULT = A ^ B;       // XOR
            3'b101: RESULT = ~A;          // NOT
            3'b110: RESULT = A + 8'd1;    // INCREMENT
            3'b111: RESULT = A - 8'd1;    // DECREMENT

            default: RESULT = 8'b0;

        endcase

        if (RESULT == 8'b0)
            ZERO = 1'b1;
        else
            ZERO = 1'b0;

    end

endmodule

rtl/register_file.v
module register_file (
    input        clk,
    input        reset,

    input        reg_write,
    input  [2:0] read_addr1,
    input  [2:0] read_addr2,
    input  [2:0] write_addr,

    input  [7:0] write_data,

    output [7:0] read_data1,
    output [7:0] read_data2
);

    reg [7:0] registers [0:7];

    integer i;

    always @(posedge clk) begin

        if (reset) begin

            for (i = 0; i < 8; i = i + 1)
                registers[i] <= 8'b0;

        end

        else if (reg_write && (write_addr != 3'b000)) begin
            registers[write_addr] <= write_data;
        end

    end

    assign read_data1 = (read_addr1 == 3'b000) ? 8'b0 :
                        registers[read_addr1];

    assign read_data2 = (read_addr2 == 3'b000) ? 8'b0 :
                        registers[read_addr2];

endmodule

rtl/control_unit.v
module control_unit (
    input  [3:0] opcode,

    output reg       reg_write,
    output reg       mem_read,
    output reg       mem_write,
    output reg       alu_src,
    output reg [2:0] alu_sel,
    output reg       mem_to_reg,
    output reg       immediate
);

    always @(*) begin

        // Default values
        reg_write = 1'b0;
        mem_read = 1'b0;
        mem_write = 1'b0;
        alu_src = 1'b0;
        alu_sel = 3'b000;
        mem_to_reg = 1'b0;
        immediate = 1'b0;

        case (opcode)

            // ADD
            4'b0000: begin
                reg_write = 1'b1;
                alu_sel = 3'b000;
            end

            // SUB
            4'b0001: begin
                reg_write = 1'b1;
                alu_sel = 3'b001;
            end

            // AND
            4'b0010: begin
                reg_write = 1'b1;
                alu_sel = 3'b010;
            end

            // OR
            4'b0011: begin
                reg_write = 1'b1;
                alu_sel = 3'b011;
            end

            // XOR
            4'b0100: begin
                reg_write = 1'b1;
                alu_sel = 3'b100;
            end

            // MOVI
            4'b0101: begin
                reg_write = 1'b1;
                alu_src = 1'b1;
                immediate = 1'b1;
            end

            // LOAD
            4'b0110: begin
                reg_write = 1'b1;
                mem_read = 1'b1;
                mem_to_reg = 1'b1;
                alu_src = 1'b1;
                immediate = 1'b1;
            end

            // STORE
            4'b0111: begin
                mem_write = 1'b1;
                alu_src = 1'b1;
                immediate = 1'b1;
            end

            default: begin
                reg_write = 1'b0;
            end

        endcase

    end

endmodule

rtl/instruction_memory.v
module instruction_memory (
    input  [7:0] address,
    output [15:0] instruction
);

    reg [15:0] memory [0:255];

    assign instruction = memory[address];

endmodule

rtl/risc_cpu.v
module risc_cpu (
    input clk,
    input reset,

    output [7:0] pc,
    output [15:0] instruction,
    output [7:0] alu_result,
    output [7:0] write_back_data
);

    // ==========================================
    // Program Counter
    // ==========================================

    reg [7:0] program_counter;

    assign pc = program_counter;


    // ==========================================
    // Instruction Memory
    // ==========================================

    wire [15:0] current_instruction;

    instruction_memory instruction_mem (
        .address(program_counter),
        .instruction(current_instruction)
    );

    assign instruction = current_instruction;


    // ==========================================
    // Instruction Fields
    // ==========================================

    wire [3:0] opcode;
    wire [2:0] rd;
    wire [2:0] rs1;
    wire [2:0] rs2;

    assign opcode = current_instruction[15:12];
    assign rd     = current_instruction[11:9];
    assign rs1    = current_instruction[8:6];
    assign rs2    = current_instruction[5:3];


    // ==========================================
    // Control Unit
    // ==========================================

    wire reg_write;
    wire mem_read;
    wire mem_write;
    wire alu_src;
    wire [2:0] alu_sel;
    wire mem_to_reg;
    wire immediate;

    control_unit control (
        .opcode(opcode),
        .reg_write(reg_write),
        .mem_read(mem_read),
        .mem_write(mem_write),
        .alu_src(alu_src),
        .alu_sel(alu_sel),
        .mem_to_reg(mem_to_reg),
        .immediate(immediate)
    );


    // ==========================================
    // Register File
    // ==========================================

    wire [7:0] register_data1;
    wire [7:0] register_data2;

    reg [7:0] register_write_data;

    register_file registers (
        .clk(clk),
        .reset(reset),

        .reg_write(reg_write),

        .read_addr1(rs1),
        .read_addr2(rs2),

        .write_addr(rd),
        .write_data(register_write_data),

        .read_data1(register_data1),
        .read_data2(register_data2)
    );


    // ==========================================
    // ALU Input Selection
    // ==========================================

    reg [7:0] alu_input_b;

    always @(*) begin

        if (immediate)
            alu_input_b = {2'b00, current_instruction[5:0]};
        else
            alu_input_b = register_data2;

    end


    // ==========================================
    // ALU
    // ==========================================

    wire [7:0] alu_output;
    wire zero_flag;

    alu processor_alu (
        .A(register_data1),
        .B(alu_input_b),
        .ALU_SEL(alu_sel),
        .RESULT(alu_output),
        .ZERO(zero_flag)
    );

    assign alu_result = alu_output;


    // ==========================================
    // Data Memory
    // ==========================================

    wire [7:0] memory_read_data;

    data_memory data_mem (
        .clk(clk),
        .mem_read(mem_read),
        .mem_write(mem_write),

        .address(current_instruction[7:0]),
        .write_data(register_data1),

        .read_data(memory_read_data)
    );


    // ==========================================
    // Write Back
    // ==========================================

    always @(*) begin

        if (mem_to_reg)
            register_write_data = memory_read_data;

        else if (opcode == 4'b0101)
            register_write_data = current_instruction[7:0];

        else
            register_write_data = alu_output;

    end

    assign write_back_data = register_write_data;


    // ==========================================
    // Program Counter Update
    // ==========================================

    always @(posedge clk) begin

        if (reset)
            program_counter <= 8'd0;

        else
            program_counter <= program_counter + 8'd1;

    end

endmodule

tb/risc_cpu_tb.v
`timescale 1ns/1ps

module risc_cpu_tb;

    reg clk;
    reg reset;

    wire [7:0] pc;
    wire [15:0] instruction;
    wire [7:0] alu_result;
    wire [7:0] write_back_data;

    // ==========================================
    // CPU
    // ==========================================

    risc_cpu uut (
        .clk(clk),
        .reset(reset),
        .pc(pc),
        .instruction(instruction),
        .alu_result(alu_result),
        .write_back_data(write_back_data)
    );

    // Clock: 10 ns period
    always #5 clk = ~clk;


    // ==========================================
    // Test Program
    // ==========================================

    initial begin

        // MOVI R1, 10
        uut.instruction_mem.memory[0] =
            {4'b0101, 3'b001, 9'b000001010};

        // MOVI R2, 5
        uut.instruction_mem.memory[1] =
            {4'b0101, 3'b010, 9'b000000101};

        // ADD R3, R1, R2
        uut.instruction_mem.memory[2] =
            {4'b0000, 3'b011, 3'b001, 3'b010, 3'b000};

        // SUB R4, R1, R2
        uut.instruction_mem.memory[3] =
            {4'b0001, 3'b100, 3'b001, 3'b010, 3'b000};

        // AND R5, R1, R2
        uut.instruction_mem.memory[4] =
            {4'b0010, 3'b101, 3'b001, 3'b010, 3'b000};

        // OR R6, R1, R2
        uut.instruction_mem.memory[5] =
            {4'b0011, 3'b110, 3'b001, 3'b010, 3'b000};

    end


    // ==========================================
    // Simulation
    // ==========================================

    initial begin

        $dumpfile("simulation/risc_cpu.vcd");
        $dumpvars(0, risc_cpu_tb);

        clk = 0;
        reset = 1;

        #12;

        reset = 0;

        #70;

        $display("");
        $display("======================================");
        $display("        RISC CPU TEST RESULTS         ");
        $display("======================================");

        $display("R1 = %d", uut.registers.registers[1]);
        $display("R2 = %d", uut.registers.registers[2]);
        $display("R3 = %d", uut.registers.registers[3]);
        $display("R4 = %d", uut.registers.registers[4]);
        $display("R5 = %d", uut.registers.registers[5]);
        $display("R6 = %d", uut.registers.registers[6]);

        $display("======================================");

        if (uut.registers.registers[1] == 10 &&
            uut.registers.registers[2] == 5 &&
            uut.registers.registers[3] == 15 &&
            uut.registers.registers[4] == 5 &&
            uut.registers.registers[5] == 0 &&
            uut.registers.registers[6] == 15)

            $display("RISC CPU SUCCESS: All instructions executed correctly!");

        else
            $display("RISC CPU TEST FAILED!");

        $display("======================================");

        $finish;

    end

endmodule

simulation/risc_cpu.vcd
$date
	Wed Aug 26 21:56:25 2026
$end
$version
	Icarus Verilog
$end
$timescale
	1ps
$end
$scope module risc_cpu_tb $end
$var wire 8 ! write_back_data [7:0] $end
$var wire 8 " pc [7:0] $end
$var wire 16 # instruction [15:0] $end
$var wire 8 $ alu_result [7:0] $end
$var reg 1 % clk $end
$var reg 1 & reset $end
$scope module uut $end
$var wire 8 ' alu_result [7:0] $end
$var wire 1 % clk $end
$var wire 16 ( instruction [15:0] $end
$var wire 8 ) pc [7:0] $end
$var wire 1 & reset $end
$var wire 8 * write_back_data [7:0] $end
$var wire 1 + zero_flag $end
$var wire 3 , rs2 [2:0] $end
$var wire 3 - rs1 [2:0] $end
$var wire 8 . register_data2 [7:0] $end
$var wire 8 / register_data1 [7:0] $end
$var wire 1 0 reg_write $end
$var wire 3 1 rd [2:0] $end
$var wire 4 2 opcode [3:0] $end
$var wire 8 3 memory_read_data [7:0] $end
$var wire 1 4 mem_write $end
$var wire 1 5 mem_to_reg $end
$var wire 1 6 mem_read $end
$var wire 1 7 immediate $end
$var wire 16 8 current_instruction [15:0] $end
$var wire 1 9 alu_src $end
$var wire 3 : alu_sel [2:0] $end
$var wire 8 ; alu_output [7:0] $end
$var reg 8 < alu_input_b [7:0] $end
$var reg 8 = program_counter [7:0] $end
$var reg 8 > register_write_data [7:0] $end
$scope module control $end
$var wire 4 ? opcode [3:0] $end
$var reg 3 @ alu_sel [2:0] $end
$var reg 1 9 alu_src $end
$var reg 1 7 immediate $end
$var reg 1 6 mem_read $end
$var reg 1 5 mem_to_reg $end
$var reg 1 4 mem_write $end
$var reg 1 0 reg_write $end
$upscope $end
$scope module data_mem $end
$var wire 8 A address [7:0] $end
$var wire 1 % clk $end
$var wire 1 6 mem_read $end
$var wire 1 4 mem_write $end
$var wire 8 B write_data [7:0] $end
$var wire 8 C read_data [7:0] $end
$upscope $end
$scope module instruction_mem $end
$var wire 8 D address [7:0] $end
$var wire 16 E instruction [15:0] $end
$upscope $end
$scope module processor_alu $end
$var wire 3 F ALU_SEL [2:0] $end
$var wire 8 G B [7:0] $end
$var wire 8 H A [7:0] $end
$var reg 8 I RESULT [7:0] $end
$var reg 1 + ZERO $end
$upscope $end
$scope module registers $end
$var wire 1 % clk $end
$var wire 3 J read_addr1 [2:0] $end
$var wire 3 K read_addr2 [2:0] $end
$var wire 1 0 reg_write $end
$var wire 1 & reset $end
$var wire 3 L write_addr [2:0] $end
$var wire 8 M write_data [7:0] $end
$var wire 8 N read_data2 [7:0] $end
$var wire 8 O read_data1 [7:0] $end
$var integer 32 P i [31:0] $end
$upscope $end
$upscope $end
$upscope $end
$enddefinitions $end
$comment Show the parameter values. $end
$dumpall
$end
#0
$dumpvars
bx P
bx O
bx N
bx M
bx L
bx K
bx J
bx I
bx H
bx G
bx F
bx E
bx D
bx C
bx B
bx A
bx @
bx ?
bx >
bx =
bx <
bx ;
bx :
x9
bx 8
x7
x6
x5
x4
bx 3
bx 2
bx 1
x0
bx /
bx .
bx -
bx ,
x+
bx *
bx )
bx (
bx '
1&
0%
bx $
bx #
bx "
bx !
$end
#5000
b1010 $
b1010 '
b1010 ;
b1010 I
b1010 <
b1010 G
0+
b0 3
b0 C
b0 .
b0 N
b0 /
b0 B
b0 H
b0 O
17
05
b0 :
b0 @
b0 F
19
04
06
10
b1010 !
b1010 *
b1010 >
b1010 M
b1010 A
b1 ,
b1 K
b0 -
b0 J
b1 1
b1 L
b101 2
b101 ?
b101001000001010 #
b101001000001010 (
b101001000001010 8
b101001000001010 E
b0 "
b0 )
b0 =
b0 D
b1000 P
1%
#10000
0%
#12000
0&
#15000
b101 $
b101 '
b101 ;
b101 I
b101 A
b0 ,
b0 K
b10 1
b10 L
b101 !
b101 *
b101 >
b101 M
b101 <
b101 G
b101010000000101 #
b101010000000101 (
b101010000000101 8
b101010000000101 E
b0 .
b0 N
b1 "
b1 )
b1 =
b1 D
1%
#20000
0%
#25000
b101 .
b101 N
b1010 /
b1010 B
b1010 H
b1010 O
07
09
10
b1111 $
b1111 '
b1111 ;
b1111 I
b1010000 A
b10 ,
b10 K
b1 -
b1 J
b11 1
b11 L
b0 2
b0 ?
b101 <
b101 G
b1111 !
b1111 *
b1111 >
b1111 M
b11001010000 #
b11001010000 (
b11001010000 8
b11001010000 E
b10 "
b10 )
b10 =
b10 D
1%
#30000
0%
#35000
b101 !
b101 *
b101 >
b101 M
b101 $
b101 '
b101 ;
b101 I
b1 :
b1 @
b1 F
10
b100 1
b100 L
b1 2
b1 ?
b1100001010000 #
b1100001010000 (
b1100001010000 8
b1100001010000 E
b11 "
b11 )
b11 =
b11 D
1%
#40000
0%
#45000
b0 !
b0 *
b0 >
b0 M
1+
b0 $
b0 '
b0 ;
b0 I
b10 :
b10 @
b10 F
10
b101 1
b101 L
b10 2
b10 ?
b10101001010000 #
b10101001010000 (
b10101001010000 8
b10101001010000 E
b100 "
b100 )
b100 =
b100 D
1%
#50000
0%
#55000
b1111 !
b1111 *
b1111 >
b1111 M
0+
b1111 $
b1111 '
b1111 ;
b1111 I
b11 :
b11 @
b11 F
10
b110 1
b110 L
b11 2
b11 ?
b11110001010000 #
b11110001010000 (
b11110001010000 8
b11110001010000 E
b101 "
b101 )
b101 =
b101 D
1%
#60000
0%
#65000
bx !
bx *
bx >
bx M
bx <
bx G
bx $
bx '
bx ;
bx I
bx .
bx N
bx /
bx B
bx H
bx O
b0 :
b0 @
b0 F
00
bx A
bx ,
bx K
bx -
bx J
bx 1
bx L
bx 2
bx ?
bx #
bx (
bx 8
bx E
b110 "
b110 )
b110 =
b110 D
1%
#70000
0%
#75000
b111 "
b111 )
b111 =
b111 D
1%
